discofy/__init__.py
discofy-1.3.dist-info/LICENSE.txt
discofy-1.3.dist-info/METADATA
discofy-1.3.dist-info/WHEEL
discofy-1.3.dist-info/top_level.txt
discofy-1.3.dist-info/RECORD
