Metadata-Version: 2.1
Name: discofy
Version: 1.3
Summary: Discofy allows control of Spotify playback through Discord API, offering features like play/pause, track skipping, volume control, and device management.
Home-page: 
Author: Echopixel
Author-email: echopixel@proton.me
License: CC BY-SA 4.0
Project-URL: Documentation, https://github.com/0EchoPixel/Discofy/blob/main/README.md
Keywords: spotify
Classifier: Development Status :: 5 - Production/Stable
Classifier: Operating System :: Microsoft :: Windows
Classifier: Programming Language :: Python :: 3
License-File: LICENSE.txt
Provides-Extra: dev
Requires-Dist: pytest>=7.0; extra == "dev"
Requires-Dist: twine>=4.0.2; extra == "dev"
